mgm/__init__.py
mgm/version.py
mgm/CLI/CLI_utils.py
mgm/CLI/__init__.py
mgm/CLI/main.py
mgm/CLI/main_construct.py
mgm/CLI/main_finetune.py
mgm/CLI/main_generate.py
mgm/CLI/main_predict.py
mgm/CLI/main_pretrain.py
mgm/CLI/main_reconstruct.py
mgm/CLI/main_train.py
mgm/resources/MicroTokenizer.pkl
mgm/resources/config.ini
mgm/resources/phylogeny.csv
mgm/resources/general_model/config.json
mgm/resources/general_model/generation_config.json
mgm/resources/general_model/pytorch_model.bin
mgm/resources/general_model/training_args.bin
mgm/src/MicroCorpus.py
mgm/src/MultiLabel_utils.py
mgm/src/Reconstructor.py
mgm/src/__init__.py
mgm/src/evaluator.py
mgm/src/utils.py
microformer_mgm-0.5.7.dist-info/LICENSE
microformer_mgm-0.5.7.dist-info/METADATA
microformer_mgm-0.5.7.dist-info/WHEEL
microformer_mgm-0.5.7.dist-info/entry_points.txt
microformer_mgm-0.5.7.dist-info/top_level.txt
microformer_mgm-0.5.7.dist-info/zip-safe
microformer_mgm-0.5.7.dist-info/RECORD
