Metadata-Version: 2.1
Name: microformer-mgm
Version: 0.5.7
Summary: MGM (Microbial General Model) as a large-scaled pretrained language model for interpretable microbiome data analysis.
Home-page: https://github.com/HUST-NingKang-Lab/MGM
Author: Haohong Zhang
Author-email: haohongzh@gmail.com
License: MIT
Classifier: Topic :: Scientific/Engineering :: Bio-Informatics
Classifier: Programming Language :: Python :: 3.9
Classifier: Development Status :: 4 - Beta
Classifier: License :: OSI Approved :: MIT License
Classifier: Operating System :: OS Independent
Classifier: Natural Language :: English
Requires-Python: >=3.9
License-File: LICENSE
Requires-Dist: numpy (==1.24.3)
Requires-Dist: pandas (==2.0.3)
Requires-Dist: pytorch-lightning (==2.0.6)
Requires-Dist: scikit-learn (==1.3.1)
Requires-Dist: setuptools (==68.0.0)
Requires-Dist: torch (==2.0.1)
Requires-Dist: tqdm (==4.65.0)
Requires-Dist: transformers (==4.33.3)
Requires-Dist: accelerate (>=0.20.1)
